diemlib/__init__.py
diemlib/box.py
diemlib/config.py
diemlib/filehandler.py
diemlib/jobhandler.py
diemlib/mailhandler.py
diemlib/main.py
diemlib/util.py
diemlib-1.1.4.dist-info/LICENSE
diemlib-1.1.4.dist-info/METADATA
diemlib-1.1.4.dist-info/WHEEL
diemlib-1.1.4.dist-info/top_level.txt
diemlib-1.1.4.dist-info/RECORD
