Metadata-Version: 2.1
Name: diemlib
Version: 1.1.4
Summary: Python Utilities for DIEM
Home-page: https://github.com/IBM/diem/tree/main/packages/diemlib
Author: Guy Huinen
Author-email: guy_huinen@be.ibm.com
License: MIT
Platform: UNKNOWN
Classifier: Programming Language :: Python :: 3
Classifier: License :: OSI Approved :: MIT License
Classifier: Operating System :: OS Independent
Requires-Python: >=3.7
